{
    "benchmarks": [
        {
            "runs": [
                {
                    "values": [
                        0.042371524,
                        0.036486556,
                        0.0395348816,
                        0.0374617050909091,
                        0.0368864460909091
                    ]
                }
            ]
        }
    ],
    "metadata": {
        "loops": 52,
        "inner_loops": 1,
        "name": "benchmark",
        "unit": "second"
    },
    "version": "1.0"
}